easygoogle/__init__.py
easygoogle/_patch_resources.py
easygoogle/apis.json
easygoogle/config.py
easygoogle/constants.py
easygoogle/controllers/__init__.py
easygoogle/controllers/base.py
easygoogle/controllers/oauth2.py
easygoogle/controllers/service_account.py
easygoogle-1.5.4.dist-info/LICENSE
easygoogle-1.5.4.dist-info/METADATA
easygoogle-1.5.4.dist-info/WHEEL
easygoogle-1.5.4.dist-info/entry_points.txt
easygoogle-1.5.4.dist-info/top_level.txt
easygoogle-1.5.4.dist-info/RECORD
