Metadata-Version: 2.1
Name: easygoogle
Version: 1.5.4
Summary: Easy to use wrapper to google APIs client library
Home-page: https://github.com/Fryuni/easygoogle
Author: Luiz Augusto Ferraz
Author-email: luiz@lferraz.com
License: Apache License 2.0
Download-URL: https://github.com/Fryuni/easygoogle/archive/release-1.5.4.tar.gz
Keywords: google apis google-apis
Platform: UNKNOWN
Classifier: Development Status :: 5 - Production/Stable
Classifier: Intended Audience :: Developers
Classifier: Intended Audience :: Education
Classifier: Intended Audience :: Information Technology
Classifier: License :: OSI Approved :: Apache Software License
Classifier: Topic :: Internet :: WWW/HTTP :: HTTP Servers
Classifier: Topic :: Utilities
Requires-Dist: google-api-python-client (~=1.7.10)
Requires-Dist: google-auth (~=1.6.3)
Requires-Dist: google-auth-oauthlib (~=0.4.0)
